thatdslibrary/__init__.py
thatdslibrary/chart_plotting.py
thatdslibrary/data_preprocessing.py
thatdslibrary/hypo_testing.py
thatdslibrary/ml_helpers.py
thatdslibrary-0.0.2.dist-info/METADATA
thatdslibrary-0.0.2.dist-info/WHEEL
thatdslibrary-0.0.2.dist-info/licenses/LICENSE
thatdslibrary-0.0.2.dist-info/RECORD
