Metadata-Version: 2.1
Name: thatdslibrary
Version: 0.0.2
Summary: A useful package for EDA and quick ML model finetuning
Project-URL: Homepage, https://github.com/anhquan0412/that_ds_library
Project-URL: Bug Tracker, https://github.com/anhquan0412/that_ds_library/issues
Author-email: Quan Tran <quan.tran1@outlook.com>
License: MIT License
License-File: LICENSE
Keywords: auto finetuning,automation,finetune,machine learning,sklearn
Classifier: License :: OSI Approved :: MIT License
Classifier: Operating System :: OS Independent
Classifier: Programming Language :: Python :: 3
Requires-Python: >=3.7
Requires-Dist: dtreeviz>=2.2
Requires-Dist: matplotlib>=3.7.0
Requires-Dist: numpy>=1.23.0
Requires-Dist: pandas>=1.5.0
Requires-Dist: pingouin>=0.5.3
Requires-Dist: plotly>=5.14.0
Requires-Dist: scikit-learn>=1.2.0
Requires-Dist: seaborn>=0.12.0
Requires-Dist: statsmodels>=0.13.0
